{
	"archive" : {},
	"artifacts" : 
	[
		{
			"path" : "Server/box2d-main/bin/libsajson.a"
		}
	],
	"backtrace" : 1,
	"backtraceGraph" : 
	{
		"commands" : 
		[
			"add_library",
			"target_include_directories",
			"set_target_properties"
		],
		"files" : 
		[
			"Server/box2d-main/extern/sajson/CMakeLists.txt"
		],
		"nodes" : 
		[
			{
				"file" : 0
			},
			{
				"command" : 0,
				"file" : 0,
				"line" : 1,
				"parent" : 0
			},
			{
				"command" : 1,
				"file" : 0,
				"line" : 2,
				"parent" : 0
			},
			{
				"command" : 2,
				"file" : 0,
				"line" : 4,
				"parent" : 0
			}
		]
	},
	"compileGroups" : 
	[
		{
			"compileCommandFragments" : 
			[
				{
					"fragment" : "-g -fvisibility=hidden -fvisibility-inlines-hidden -fdiagnostics-color=always"
				},
				{
					"fragment" : "-std=c++11"
				}
			],
			"includes" : 
			[
				{
					"backtrace" : 2,
					"path" : "/home/abraham/Escritorio/Taller/TPS-Taller-20232C/Worms-Taller-1/Server/box2d-main/extern/sajson/.."
				}
			],
			"language" : "CXX",
			"languageStandard" : 
			{
				"backtraces" : 
				[
					3
				],
				"standard" : "11"
			},
			"sourceIndexes" : 
			[
				0
			]
		}
	],
	"id" : "sajson::@0d519826222a809ebc97",
	"name" : "sajson",
	"nameOnDisk" : "libsajson.a",
	"paths" : 
	{
		"build" : "Server/box2d-main/extern/sajson",
		"source" : "Server/box2d-main/extern/sajson"
	},
	"sourceGroups" : 
	[
		{
			"name" : "",
			"sourceIndexes" : 
			[
				0,
				1
			]
		}
	],
	"sources" : 
	[
		{
			"backtrace" : 1,
			"compileGroupIndex" : 0,
			"path" : "Server/box2d-main/extern/sajson/sajson.cpp",
			"sourceGroupIndex" : 0
		},
		{
			"backtrace" : 1,
			"path" : "Server/box2d-main/extern/sajson/sajson.h",
			"sourceGroupIndex" : 0
		}
	],
	"type" : "STATIC_LIBRARY"
}
